InfraFair/InfraFair.py
InfraFair/__init__.py
InfraFair-1.3.2.dist-info/LICENSE
InfraFair-1.3.2.dist-info/LICENSE.txt
InfraFair-1.3.2.dist-info/METADATA
InfraFair-1.3.2.dist-info/WHEEL
InfraFair-1.3.2.dist-info/dependency_links.txt
InfraFair-1.3.2.dist-info/top_level.txt
InfraFair-1.3.2.dist-info/RECORD
