Metadata-Version: 2.1
Name: InfraFair
Version: 1.3.2
Summary: A modelling tool for infrastructure cost allocation
Home-page: https://github.com/IIT-EnergySystemModels/InfraFair
Author: Mohamed A.Eltahir Elabbas
Author-email: mohamed.a.eltahir@hotmail.com
License: GNU AFFERO General Public License v3
Classifier: Development Status :: 5 - Production/Stable
Classifier: Intended Audience :: Science/Research
Classifier: Environment :: Console
Classifier: License :: OSI Approved :: GNU Affero General Public License v3
Classifier: Operating System :: OS Independent
Classifier: Natural Language :: English
Classifier: Programming Language :: Python :: 3.8
Classifier: Programming Language :: Python :: 3.9
Classifier: Programming Language :: Python :: 3.10
Classifier: Programming Language :: Python :: 3.11
Classifier: Programming Language :: Python :: 3.12
Classifier: Programming Language :: Python :: 3.13
Requires-Python: >=3.8
License-File: LICENSE
License-File: LICENSE.txt
Requires-Dist: numpy >=1.23.0
Requires-Dist: pandas >=1.3.4
Requires-Dist: matplotlib >=3.5.0
Requires-Dist: openpyxl >=3.0.0
